{"authorDailyContributionsMap":{"kihoo56tkr":[{"date":"2026-03-01T00:00:00","commitResults":[{"hash":"950ea48ba2ee050e0e9e6f0a985a1fa265c2a82e","isMergeCommit":false,"messageTitle":"Update AboutUs page (Kin Ru)","messageBody":"","fileTypesAndContributionMap":{"docs":{"insertions":3,"deletions":3}}}]}],"CrunchyBiscuit19":[{"date":"2026-03-01T00:00:00","commitResults":[{"hash":"3d6c8470b73d16a2fcdf972f9f9bdb4a5196937f","isMergeCommit":false,"messageTitle":"Edit AboutUs.md for Sim Yue Yang","messageBody":"","fileTypesAndContributionMap":{"docs":{"insertions":3,"deletions":3}}}]},{"date":"2026-03-03T00:00:00","commitResults":[{"hash":"4ed4a3279905426d29d4febec3da855b2b251c85","isMergeCommit":true,"messageTitle":"Merge pull request #25 from kihoo56tkr/branch-edit-about-us","messageBody":"Update AboutUs page (Kin Ru)\n\nClose #20","fileTypesAndContributionMap":{}},{"hash":"372a01f0da87562f00c9ea8ce1b0d4b876a84789","isMergeCommit":true,"messageTitle":"Merge branch \u0027master\u0027 into branch-edit-aboutus","messageBody":"","fileTypesAndContributionMap":{}},{"hash":"6cff0cacf4d334fc7c111a9e047fbfd5b2d77c3d","isMergeCommit":true,"messageTitle":"Merge pull request #27 from Jaejun02/branch-update-aboutus","messageBody":"Update AboutUs page (Jaejun)\n\nClose #21","fileTypesAndContributionMap":{}},{"hash":"dac63881dec70a69299685bb7adb5144f933b0e4","isMergeCommit":true,"messageTitle":"Merge pull request #23 from sherylphoa/update-about-us-sheryl","messageBody":"Update AboutUs for Sheryl\n\nClose #19\n","fileTypesAndContributionMap":{}}]},{"date":"2026-03-04T00:00:00","commitResults":[{"hash":"dcdb866f6f94bb8cc33679157976d804673a6c77","isMergeCommit":true,"messageTitle":"Merge branch \u0027master\u0027 into Update-AboutUs","messageBody":"","fileTypesAndContributionMap":{}},{"hash":"032a277b6bde49a834bac542f2ec066bbea12181","isMergeCommit":true,"messageTitle":"Merge pull request #24 from huiyi-Al/Update-AboutUs","messageBody":"Update AboutUs page\n\nClose #18","fileTypesAndContributionMap":{}},{"hash":"327fa30e49d9f2373339a247955bdfa4dd8ace0b","isMergeCommit":false,"messageTitle":"Fix typo in image name","messageBody":"","fileTypesAndContributionMap":{"docs":{"insertions":1,"deletions":1}}}]}],"huiyi-Al":[{"date":"2026-03-01T00:00:00","commitResults":[{"hash":"d6abf813c7f4fa84ba2a8631cb5ef08481847a89","isMergeCommit":false,"messageTitle":"edit AboutUs","messageBody":"","fileTypesAndContributionMap":{"docs":{"insertions":3,"deletions":3}}}]}],"sherylphoa":[{"date":"2026-03-01T00:00:00","commitResults":[{"hash":"675dd7c9e4ad87539c0583359b41cc0b8b642dfb","isMergeCommit":false,"messageTitle":"Update AboutUs for Sheryl","messageBody":"","fileTypesAndContributionMap":{"docs":{"insertions":2,"deletions":2}}}]},{"date":"2026-03-03T00:00:00","commitResults":[{"hash":"0eca928d087fda65eef8810427df809384119032","isMergeCommit":true,"messageTitle":"Resolve merge conflict","messageBody":"","fileTypesAndContributionMap":{}},{"hash":"98d79c8a32e5e3c2a789a75cf967b37cd735044d","isMergeCommit":false,"messageTitle":"Resolve build error","messageBody":"","fileTypesAndContributionMap":{"docs":{"insertions":1,"deletions":1}}}]}],"Jaejun02":[{"date":"2026-03-01T00:00:00","commitResults":[{"hash":"bb5dc54fd5eadeadf03cf8cb806fd280d8c4abee","isMergeCommit":false,"messageTitle":"Update AboutUs section for Jaejun","messageBody":"","fileTypesAndContributionMap":{"docs":{"insertions":3,"deletions":44}}}]},{"date":"2026-03-03T00:00:00","commitResults":[{"hash":"089a0cc8ed9f67f584b416338ee0e762b9e63fe1","isMergeCommit":true,"messageTitle":"Merge pull request #26 from CrunchyBiscuit19/branch-edit-aboutus","messageBody":"Edit AboutUs.md for Sim Yue Yang","fileTypesAndContributionMap":{}},{"hash":"cf4b78c81e8a90ece6906e79d33df29bcc975ccb","isMergeCommit":true,"messageTitle":"Merge branch \u0027master\u0027 into branch-update-aboutus","messageBody":"","fileTypesAndContributionMap":{}}]},{"date":"2026-03-04T00:00:00","commitResults":[{"hash":"bb16af6d261ba476d8884e5ff9019a968c3da7e1","isMergeCommit":true,"messageTitle":"Merge pull request #38 from CrunchyBiscuit19/branch-fix-typo-image-name","messageBody":"Fix typo in image name","fileTypesAndContributionMap":{}}]}]},"authorFileTypeContributionMap":{"kihoo56tkr":{"docs":3,"functional-code":0,"test-code":0},"CrunchyBiscuit19":{"docs":4,"functional-code":0,"test-code":0},"huiyi-Al":{"docs":0,"functional-code":0,"test-code":0},"sherylphoa":{"docs":4,"functional-code":0,"test-code":0},"Jaejun02":{"docs":8,"functional-code":0,"test-code":0}},"authorContributionVariance":{"kihoo56tkr":2.556213,"CrunchyBiscuit19":2.6982245,"huiyi-Al":2.556213,"sherylphoa":1.3254437,"Jaejun02":156.85208},"authorDisplayNameMap":{"kihoo56tkr":"CS2103-F09-4 TAN ..N RU","CrunchyBiscuit19":"CS2103-F09-4 SIM ..YANG","huiyi-Al":"CS2103-F09-4 LIU ..IYUE","sherylphoa":"CS2103-F09-4 PHOA..ERYL","Jaejun02":"CS2103-F09-4 SHIM..EJUN"}}
