{"authorDailyContributionsMap":{"Arkanian4":[{"date":"2026-02-28T00:00:00","commitResults":[{"hash":"056f8e52900ab163ff866784e756e17ba5d9be78","isMergeCommit":false,"messageTitle":"Update AboutUs page","messageBody":"","fileTypesAndContributionMap":{"docs":{"insertions":3,"deletions":3}}},{"hash":"3000d3dfac2b271dc3534b5ad3cb64cd6aaebb8a","isMergeCommit":true,"messageTitle":"Merge pull request #25 from Arkanian4/Add-AboutUs-Page","messageBody":"Update AboutUs page","fileTypesAndContributionMap":{}}]}],"concentratedsulfuricacid":[{"date":"2026-02-27T00:00:00","commitResults":[{"hash":"9848e701458d166fc15cbcef4f04bde4e157baba","isMergeCommit":false,"messageTitle":"Update AboutUs","messageBody":"","fileTypesAndContributionMap":{"docs":{"insertions":3,"deletions":4}}}]},{"date":"2026-02-28T00:00:00","commitResults":[{"hash":"a35375f3bbd9d58a3e556ab9dcfa57044ee6735b","isMergeCommit":true,"messageTitle":"Merge pull request #23 from concentratedsulfuricacid/branch-AboutUs","messageBody":"Update AboutUs","fileTypesAndContributionMap":{}}]}],"lemonishi":[{"date":"2026-02-27T00:00:00","commitResults":[{"hash":"40d3afa4cd5d73f2d369dc991a59b98ccaae3734","isMergeCommit":true,"messageTitle":"Merge pull request #13 from lemonishi/branch-add-lennon-photo","messageBody":"feat: Add Lennon\u0027s photo","fileTypesAndContributionMap":{}},{"hash":"b5b8799ba385c254af3474e1fd5745373a7ff4b2","isMergeCommit":false,"messageTitle":"chore: Update Lennon\u0027s AboutUs page","messageBody":"","fileTypesAndContributionMap":{"docs":{"insertions":3,"deletions":3}}}]},{"date":"2026-02-28T00:00:00","commitResults":[{"hash":"e02646d3c11a7948c13eff3215ec462c81dadb47","isMergeCommit":true,"messageTitle":"Merge branch \u0027master\u0027 into branch-update-lennon-aboutus","messageBody":"","fileTypesAndContributionMap":{}},{"hash":"1979469c1e5e56d4c3d1ae6d25ee07197ebfe7dc","isMergeCommit":true,"messageTitle":"Merge pull request #22 from lemonishi/branch-update-lennon-aboutus","messageBody":"chore: Update Lennon\u0027s AboutUs page","fileTypesAndContributionMap":{}}]}],"cassandratay":[{"date":"2026-02-21T00:00:00","commitResults":[{"hash":"b8dd0975b9944e1df072893ae6ebd799e79121f2","isMergeCommit":true,"messageTitle":"Merge remote-tracking branch \u0027upstream/switch-docs-to-markbind\u0027","messageBody":"","fileTypesAndContributionMap":{}},{"hash":"aa2bc4114a701e8d9a83e2e4bf64f206267bb94e","isMergeCommit":false,"messageTitle":"Update MarkBind configuration","messageBody":"","fileTypesAndContributionMap":{"docs":{"insertions":1,"deletions":1}}}]},{"date":"2026-02-27T00:00:00","commitResults":[{"hash":"0bae64c3304047582109cdddee0b82f10db4ab53","isMergeCommit":false,"messageTitle":"Update AboutUs page","messageBody":"","fileTypesAndContributionMap":{"docs":{"insertions":4,"deletions":3}}}]},{"date":"2026-02-28T00:00:00","commitResults":[{"hash":"3ad61be7186ee689deb1186daf9c5b741481cf2e","isMergeCommit":true,"messageTitle":"Merge pull request #24 from cassandratay/branch-aboutus-page","messageBody":"Update AboutUs page","fileTypesAndContributionMap":{}}]}],"jaris2203":[{"date":"2026-02-28T00:00:00","commitResults":[{"hash":"7f356dd1e1068af531b0b779213092c8b26d6c34","isMergeCommit":false,"messageTitle":"Add personal picture and github link","messageBody":"","fileTypesAndContributionMap":{"docs":{"insertions":3,"deletions":3}}},{"hash":"02b2457d724cffc4d4d01dce7cfb3457d9b8ca5a","isMergeCommit":true,"messageTitle":"Merge pull request #27 from jaris2203/branch-AboutUs","messageBody":"Add personal picture and github link","fileTypesAndContributionMap":{}}]}]},"authorFileTypeContributionMap":{"Arkanian4":{"docs":0,"functional-code":0,"test-code":0},"concentratedsulfuricacid":{"docs":3,"functional-code":0,"test-code":0},"lemonishi":{"docs":6,"functional-code":0,"test-code":0},"cassandratay":{"docs":5,"functional-code":0,"test-code":0},"jaris2203":{"docs":3,"functional-code":0,"test-code":0}},"authorContributionVariance":{"Arkanian4":3.5555556,"concentratedsulfuricacid":4.839506,"lemonishi":3.5555556,"cassandratay":4.888889,"jaris2203":3.5555556},"authorDisplayNameMap":{"Arkanian4":"CS2103T-T08-3 DARR.. ZHI","concentratedsulfuricacid":"CS2103T-T08-3 DAMI..CHIN","lemonishi":"CS2103T-T08-3 LEUN..NNON","cassandratay":"CS2103T-T08-3 CASS.. TAY","jaris2203":"CS2103T-T08-3 JARI..HENG"}}
